ttk_epay/__init__.py
ttk_epay/app.py
ttk_epay/models.py
ttk_epay-0.1.6.dist-info/LICENSE
ttk_epay-0.1.6.dist-info/METADATA
ttk_epay-0.1.6.dist-info/WHEEL
ttk_epay-0.1.6.dist-info/RECORD
